[
  {
    "id": 1,
    "genre": "Sports",
    "payType": "P",
    "isLive": "true",
    "title": "Toronto Blue Jays VS New York Yankees",
    "imageUrl": "https://images.fancode.com/aig/match/v1/137571_CASACARDS_PARTNER_16_9_1920_1080.png",
    "okassetkey": "363997347879",
    "widevine_data": {
      "kid": "0c2dda78184238f6f90661d810377b2b",
      "key": "6f20d990c5f622ff88d69b2a9ecf1706"
    },
    "sources": [
      {
        "name": "HLS",
        "hls": "https://live-aws-cdn.okflix.top/hls/fan1-137571.m3u8"
      }
    ]
  },
  {
    "id": 2,
    "genre": "Sports",
    "payType": "P",
    "isLive": "true",
    "title": "Seattle Mariners VS Detroit Tigers",
    "imageUrl": "https://images.fancode.com/aig/match/v1/137570_CASACARDS_PARTNER_16_9_1920_1080.png",
    "okassetkey": "331843741339",
    "widevine_data": {
      "kid": "d582949941c81a7f257426b732f9df9c",
      "key": "b13599f78441853e9a82008b5f79a6cc"
    },
    "sources": [
      {
        "name": "HLS",
        "hls": "https://live-aws-cdn.okflix.top/hls/fan1-137570.m3u8"
      }
    ]
  },
  {
    "id": 3,
    "genre": "Sports",
    "payType": "P",
    "isLive": "true",
    "title": "Chicago CC VS Houston Generals CC",
    "imageUrl": "https://images.fancode.com/aig/match/v1/137299_CASACARDS_PARTNER_16_9_1920_1080.png",
    "okassetkey": "242533057717",
    "widevine_data": {
      "kid": "545fb89e28da0cfe7b1c1d5f060329eb",
      "key": "07dc0ed3821bfe77f1c98426b04a257e"
    },
    "sources": [
      {
        "name": "HLS",
        "hls": "https://live-aws-cdn.okflix.top/hls/fan1-137299.m3u8"
      }
    ]
  },
  {
    "id": 4,
    "genre": "Sports",
    "payType": "P",
    "isLive": "true",
    "title": "Victoria Women VS Tasmania Women",
    "imageUrl": "https://images.fancode.com/aig/match/v1/133956_CASACARDS_PARTNER_16_9_1920_1080.png",
    "okassetkey": "622437231663",
    "widevine_data": {
      "kid": "aa076bd70f4a148a97e5bfca05286869",
      "key": "217b3024dee640ce46afd7ba80898091"
    },
    "sources": [
      {
        "name": "HLS",
        "hls": "https://live-aws-cdn.okflix.top/hls/fan1-133956.m3u8"
      }
    ]
  }
]