[
  {
    "id": 1,
    "genre": "Sports",
    "payType": "P",
    "isLive": "true",
    "title": "Philadelphia Phillies VS Los Angeles Dodgers",
    "imageUrl": "https://images.fancode.com/aig/match/v1/137575_CASACARDS_PARTNER_16_9_1920_1080.png",
    "okassetkey": "803505455103",
    "widevine_data": {
      "kid": "f76f429e5e7ae9d9cd06c1a6b3613056",
      "key": "48a5b0ae6773aed0e6e2198d79bafe26"
    },
    "sources": [
      {
        "name": "HLS",
        "hls": "https://live-aws-cdn.okflix.top/hls/fan1-137575.m3u8"
      }
    ]
  },
  {
    "id": 2,
    "genre": "Sports",
    "payType": "P",
    "isLive": "true",
    "title": "Montreal Royal Tigers VS Mississauga Masters",
    "imageUrl": "https://images.fancode.com/aig/match/v1/137423_CASACARDS_PARTNER_16_9_1920_1080.png",
    "okassetkey": "389225604560",
    "widevine_data": {
      "kid": "924ff7b0e792c53530181351cf4378d5",
      "key": "bd6cb3d9ee25b416a9e5648146207879"
    },
    "sources": [
      {
        "name": "HLS",
        "hls": "https://live-aws-cdn.okflix.top/hls/fan1-137423.m3u8"
      }
    ]
  },
  {
    "id": 3,
    "genre": "Sports",
    "payType": "P",
    "isLive": "true",
    "title": "New York Lions CC VS Los Angeles Waves CC",
    "imageUrl": "https://images.fancode.com/aig/match/v1/137302_CASACARDS_PARTNER_16_9_1920_1080.png",
    "okassetkey": "407571589816",
    "widevine_data": {
      "kid": "64d22e81b4768c19408142870cc29191",
      "key": "5503553d94bc0ab5720099ffb1b50610"
    },
    "sources": [
      {
        "name": "HLS",
        "hls": "https://live-aws-cdn.okflix.top/hls/fan1-137302.m3u8"
      }
    ]
  },
  {
    "id": 4,
    "genre": "Sports",
    "payType": "P",
    "isLive": "true",
    "title": "Baycurrent Classic",
    "imageUrl": "https://images.fancode.com/aig/match/v1/137311_CASACARDS_PARTNER_16_9_1920_1080.png",
    "okassetkey": "740429550299",
    "widevine_data": {
      "kid": "a9c12998719033fb66a6a7f1861057b2",
      "key": "be87c90d1ea8cc165f404e8414e45951"
    },
    "sources": [
      {
        "name": "HLS",
        "hls": "https://live-aws-cdn.okflix.top/hls/fan1-137311.m3u8"
      }
    ]
  },
  {
    "id": 5,
    "genre": "Sports",
    "payType": "P",
    "isLive": "true",
    "title": "Queensland VS Tasmania",
    "imageUrl": "https://images.fancode.com/aig/match/v1/133935_CASACARDS_PARTNER_16_9_1920_1080.png",
    "okassetkey": "295315705647",
    "widevine_data": {
      "kid": "288acbd0b163ffe5875b8f3ff7ac5f83",
      "key": "eef3bf58afaea8822c43a4fffe98053b"
    },
    "sources": [
      {
        "name": "HLS",
        "hls": "https://live-aws-cdn.okflix.top/hls/fan1-133935.m3u8"
      }
    ]
  },
  {
    "id": 6,
    "genre": "Sports",
    "payType": "P",
    "isLive": "true",
    "title": "New South Wales Breakers VS Western Australia Women",
    "imageUrl": "https://images.fancode.com/aig/match/v1/133958_CASACARDS_PARTNER_16_9_1920_1080.png",
    "okassetkey": "959905862281",
    "widevine_data": {
      "kid": "7edd716f964039aff2c3102bb7f09d85",
      "key": "38b407bc6781ab01cf19a24d51e0219c"
    },
    "sources": [
      {
        "name": "HLS",
        "hls": "https://live-aws-cdn.okflix.top/hls/fan1-133958.m3u8"
      }
    ]
  },
  {
    "id": 7,
    "genre": "Sports",
    "payType": "P",
    "isLive": "true",
    "title": "South Australia VS Victoria",
    "imageUrl": "https://images.fancode.com/aig/match/v1/133934_CASACARDS_PARTNER_16_9_1920_1080.png",
    "okassetkey": "152841279470",
    "widevine_data": {
      "kid": "79eeba61d6d63eabd577e39e32fa1384",
      "key": "278969a696be9b443983cf7891bc3e26"
    },
    "sources": [
      {
        "name": "HLS",
        "hls": "https://live-aws-cdn.okflix.top/hls/fan1-133934.m3u8"
      }
    ]
  }
]