[
  {
    "id": 1,
    "genre": "Sports",
    "payType": "P",
    "isLive": "true",
    "title": "Milwaukee Brewers VS Chicago Cubs",
    "imageUrl": "https://images.fancode.com/aig/match/v1/137577_CASACARDS_PARTNER_16_9_1920_1080.png",
    "okassetkey": "077130472947",
    "widevine_data": {
      "kid": "a1d50b3b33b4f8759519fe2f03fd660d",
      "key": "3de39de476ea6f0566b53228c0009d52"
    },
    "sources": [
      {
        "name": "HLS",
        "hls": "https://live-aws-cdn.okflix.top/hls/fan1-137577.m3u8"
      }
    ]
  },
  {
    "id": 2,
    "genre": "Sports",
    "payType": "P",
    "isLive": "true",
    "title": "Philadelphia Phillies VS Los Angeles Dodgers",
    "imageUrl": "https://images.fancode.com/aig/match/v1/137576_CASACARDS_PARTNER_16_9_1920_1080.png",
    "okassetkey": "670112681491",
    "widevine_data": {
      "kid": "96d3a5357e906402e2ba8e99b2fb0100",
      "key": "875482ce6d0bb1433f8f716c4ac873ad"
    },
    "sources": [
      {
        "name": "HLS",
        "hls": "https://live-aws-cdn.okflix.top/hls/fan1-137576.m3u8"
      }
    ]
  },
  {
    "id": 3,
    "genre": "Sports",
    "payType": "P",
    "isLive": "true",
    "title": "Montreal Royal Tigers VS Vancouver Kings",
    "imageUrl": "https://images.fancode.com/aig/match/v1/137426_CASACARDS_PARTNER_16_9_1920_1080.png",
    "okassetkey": "671525054706",
    "widevine_data": {
      "kid": "2382d500cbe6d4970d0639cc29b929e6",
      "key": "16678bc17db3dabf5918b2d6689686cf"
    },
    "sources": [
      {
        "name": "HLS",
        "hls": "https://live-aws-cdn.okflix.top/hls/fan1-137426.m3u8"
      }
    ]
  },
  {
    "id": 4,
    "genre": "Sports",
    "payType": "P",
    "isLive": "true",
    "title": "New York Lions CC VS Houston Generals CC",
    "imageUrl": "https://images.fancode.com/aig/match/v1/137304_CASACARDS_PARTNER_16_9_1920_1080.png",
    "okassetkey": "783143919866",
    "widevine_data": {
      "kid": "272f958952393261b5e6648143b10be4",
      "key": "e1846ef685368308f330ca89bb3c8247"
    },
    "sources": [
      {
        "name": "HLS",
        "hls": "https://live-aws-cdn.okflix.top/hls/fan1-137304.m3u8"
      }
    ]
  },
  {
    "id": 5,
    "genre": "Sports",
    "payType": "P",
    "isLive": "true",
    "title": "Victoria Women VS Tasmania Women",
    "imageUrl": "https://images.fancode.com/aig/match/v1/133957_CASACARDS_PARTNER_16_9_1920_1080.png",
    "okassetkey": "585021723056",
    "widevine_data": {
      "kid": "6e241e0713256a4c8efec246dde0bd09",
      "key": "92e256ca5eda36ff8bb3178e686654e0"
    },
    "sources": [
      {
        "name": "HLS",
        "hls": "https://live-aws-cdn.okflix.top/hls/fan1-133957.m3u8"
      }
    ]
  }
]