[
  {
    "id": 1,
    "genre": "Sports",
    "payType": "P",
    "isLive": "true",
    "title": "Toronto Blue Jays VS New York Yankees",
    "imageUrl": "https://images.fancode.com/aig/match/v1/137571_CASACARDS_PARTNER_16_9_1920_1080.png",
    "okassetkey": "632547592201",
    "widevine_data": {
      "kid": "ffe88a31b81bca54687fc8752e094015",
      "key": "3f12271b0593c3f71c73eb5a20350d1f"
    },
    "sources": [
      {
        "name": "HLS",
        "hls": "https://live-aws-cdn.okflix.top/hls/fan1-137571.m3u8"
      }
    ]
  },
  {
    "id": 2,
    "genre": "Sports",
    "payType": "P",
    "isLive": "true",
    "title": "Seattle Mariners VS Detroit Tigers",
    "imageUrl": "https://images.fancode.com/aig/match/v1/137570_CASACARDS_PARTNER_16_9_1920_1080.png",
    "okassetkey": "688293964542",
    "widevine_data": {
      "kid": "a279312abd475ab018e338fb3c1df22e",
      "key": "c3b374bd4c04d099a71ca76e2f3cdb90"
    },
    "sources": [
      {
        "name": "HLS",
        "hls": "https://live-aws-cdn.okflix.top/hls/fan1-137570.m3u8"
      }
    ]
  },
  {
    "id": 3,
    "genre": "Sports",
    "payType": "P",
    "isLive": "true",
    "title": "Chicago CC VS Houston Generals CC",
    "imageUrl": "https://images.fancode.com/aig/match/v1/137299_CASACARDS_PARTNER_16_9_1920_1080.png",
    "okassetkey": "149133724780",
    "widevine_data": {
      "kid": "0176da7c0f0f30e23815d75d8a098ec3",
      "key": "f6088604ec478c337a56003caf164b9e"
    },
    "sources": [
      {
        "name": "HLS",
        "hls": "https://live-aws-cdn.okflix.top/hls/fan1-137299.m3u8"
      }
    ]
  },
  {
    "id": 4,
    "genre": "Sports",
    "payType": "P",
    "isLive": "true",
    "title": "Victoria Women VS Tasmania Women",
    "imageUrl": "https://images.fancode.com/aig/match/v1/133956_CASACARDS_PARTNER_16_9_1920_1080.png",
    "okassetkey": "123539659639",
    "widevine_data": {
      "kid": "8b095c2a69cc93ccf2cdbd2400a05088",
      "key": "935ef84644de01f78a4334d8d3a8931d"
    },
    "sources": [
      {
        "name": "HLS",
        "hls": "https://live-aws-cdn.okflix.top/hls/fan1-133956.m3u8"
      }
    ]
  }
]