[
  {
    "id": 1,
    "genre": "Sports",
    "payType": "P",
    "isLive": "true",
    "title": "Seattle Mariners VS Detroit Tigers",
    "imageUrl": "https://images.fancode.com/aig/match/v1/137570_CASACARDS_PARTNER_16_9_1920_1080.png",
    "okassetkey": "188355074799",
    "widevine_data": {
      "kid": "6463a43d10c0ecd051865f954eb8c785",
      "key": "6d62e799e2b298946ba53b58c88bc513"
    },
    "sources": [
      {
        "name": "HLS",
        "hls": "https://live-aws-cdn.okflix.top/hls/fan1-137570.m3u8"
      }
    ]
  },
  {
    "id": 2,
    "genre": "Sports",
    "payType": "P",
    "isLive": "true",
    "title": "Chicago CC VS Houston Generals CC",
    "imageUrl": "https://images.fancode.com/aig/match/v1/137299_CASACARDS_PARTNER_16_9_1920_1080.png",
    "okassetkey": "419333441451",
    "widevine_data": {
      "kid": "f80486f879ca4016958c8b159d08af2a",
      "key": "c5426eef45b4d735e61556bc197f097a"
    },
    "sources": [
      {
        "name": "HLS",
        "hls": "https://live-aws-cdn.okflix.top/hls/fan1-137299.m3u8"
      }
    ]
  },
  {
    "id": 3,
    "genre": "Sports",
    "payType": "P",
    "isLive": "true",
    "title": "Puerto Rico VS Venezuela",
    "imageUrl": "",
    "okassetkey": "280163189224",
    "widevine_data": {
      "kid": "5c7a640d6f8cc82ab6a063bfc8864019",
      "key": "2828324be901b05c164c421cb8bd27dd"
    },
    "sources": []
  },
  {
    "id": 4,
    "genre": "Sports",
    "payType": "P",
    "isLive": "true",
    "title": "Victoria Women VS Tasmania Women",
    "imageUrl": "https://images.fancode.com/aig/match/v1/133956_CASACARDS_PARTNER_16_9_1920_1080.png",
    "okassetkey": "658189240456",
    "widevine_data": {
      "kid": "372394b11cc802470794f8dfb888b167",
      "key": "c48f64b4a1802e2e01159129a19338f2"
    },
    "sources": [
      {
        "name": "HLS",
        "hls": "https://live-aws-cdn.okflix.top/hls/fan1-133956.m3u8"
      }
    ]
  },
  {
    "id": 5,
    "genre": "Sports",
    "payType": "P",
    "isLive": "true",
    "title": "Charlotte Hornets VS Memphis Grizzlies",
    "imageUrl": "",
    "okassetkey": "165044778569",
    "widevine_data": {
      "kid": "e993abf852c68688b717ea856736eb9f",
      "key": "88ce2b3e8166fe93a192435c122e1d0a"
    },
    "sources": []
  }
]