[
  {
    "id": 1,
    "genre": "Cricket",
    "payType": "P",
    "isLive": "true",
    "title": "New Zealand W vs Bangladesh W",
    "imageUrl": "https://img1.hotstarext.com/image/upload/w_720,q_auto:low,f_auto/sources/r1/cms/prod/8196/1760037258196-h",
    "okassetkey": "886053874546",
    "widevine_data": {
      "kid": "3acbd1f4a938a60ff41e942af4f4b04f",
      "key": "34f9428ed6c2e702391db033fcdce02e"
    },
    "sources": []
  },
  {
    "id": 2,
    "genre": "Cricket",
    "payType": "P",
    "isLive": "true",
    "title": "2nd Test: India vs West Indies, Day 1",
    "imageUrl": "https://img1.hotstarext.com/image/upload/w_720,q_auto:low,f_auto/sources/r1/cms/prod/9955/1760007589955-h",
    "okassetkey": "009003856870",
    "widevine_data": {
      "kid": "bff0029b783bc111fc6afba1f903936f",
      "key": "aa816bfac4c484d964b3a4016b409be9"
    },
    "sources": []
  },
  {
    "id": 3,
    "genre": "Sports",
    "payType": "P",
    "isLive": "true",
    "title": "Tamil Nadu Chief Minister\u2019s Trophy Games 2025",
    "imageUrl": "https://images.fancode.com/aig/match/v1/137419_CASACARDS_PARTNER_16_9_1920_1080.png",
    "okassetkey": "884113286798",
    "widevine_data": {
      "kid": "8f044b0324683e30c8686b64f953e310",
      "key": "b6873d2c27ba8e8f8f56af884e498ff8"
    },
    "sources": [
      {
        "name": "HLS",
        "hls": "https://live-aws-cdn.okflix.top/hls/fan1-137419.m3u8"
      }
    ]
  },
  {
    "id": 4,
    "genre": "Sports",
    "payType": "P",
    "isLive": "true",
    "title": "United Arab Emirates VS Malaysia",
    "imageUrl": "https://images.fancode.com/aig/match/v1/137180_CASACARDS_PARTNER_16_9_1920_1080.png",
    "okassetkey": "405298240927",
    "widevine_data": {
      "kid": "c937f35ccad2f45839903f02a2e0acb9",
      "key": "f6e898b926f68549c15292304af5d268"
    },
    "sources": [
      {
        "name": "HLS",
        "hls": "https://live-aws-cdn.okflix.top/hls/fan1-137180.m3u8"
      }
    ]
  }
]