[
  {
    "id": 1,
    "genre": "Cricket",
    "payType": "P",
    "isLive": "true",
    "title": "Australia W vs Pakistan W",
    "imageUrl": "https://img1.hotstarext.com/image/upload/w_720,q_auto:low,f_auto/sources/r1/cms/prod/3386/1759834923386-h",
    "okassetkey": "027463201048",
    "widevine_data": {
      "kid": "50f942b617eedc079f62626faea29ea5",
      "key": "b9d0c816abe9dcd0855a6390b592a8d6"
    },
    "sources": [
      {
        "name": "English",
        "language": "eng",
        "hls": "https://live-aws-cdn.okflix.top/hls/eng/hs-1540051848.m3u8"
      }
    ]
  },
  {
    "id": 2,
    "genre": "Tennis",
    "payType": "P",
    "isLive": "true",
    "title": "Sony Sports Ten 5",
    "imageUrl": "https://images.slivcdn.com/videoasset_images/manage_file/1000009657/175925330553358_ATP1000_Shanghai_Masters_30sep_round4_landscape_thumb.jpg?h=auto&w=720&q=low",
    "okassetkey": "886939511743",
    "widevine_data": {
      "kid": "164d8658b9b2cfbe2fc0cb2d117de2bc",
      "key": "37f3bd4305be1504f9390646a098322a"
    },
    "sources": [
      {
        "name": "English",
        "language": "ENG",
        "hls": "https://live-aws-cdn.okflix.top/hls/sliv1-1090491804.m3u8"
      }
    ]
  },
  {
    "id": 3,
    "genre": "Sports",
    "payType": "P",
    "isLive": "true",
    "title": "Mauritius VS Cameroon",
    "imageUrl": "https://images.fancode.com/aig/match/v1/137349_CASACARDS_PARTNER_16_9_1920_1080.png",
    "okassetkey": "652482525675",
    "widevine_data": {
      "kid": "54311fe6e123095aeb5ff897a8b8dfc0",
      "key": "42fbcfea371241b694c013879dfceda1"
    },
    "sources": [
      {
        "name": "HLS",
        "hls": "https://live-aws-cdn.okflix.top/hls/fan1-137349.m3u8"
      }
    ]
  },
  {
    "id": 4,
    "genre": "Sports",
    "payType": "P",
    "isLive": "true",
    "title": "Eswatini VS Angola",
    "imageUrl": "https://images.fancode.com/aig/match/v1/137351_CASACARDS_PARTNER_16_9_1920_1080.png",
    "okassetkey": "546730952325",
    "widevine_data": {
      "kid": "ace2ca0948e5d4ea657e1ebcfa2cced2",
      "key": "0dc9e8255928f3d8fa8053c807d825f7"
    },
    "sources": [
      {
        "name": "HLS",
        "hls": "https://live-aws-cdn.okflix.top/hls/fan1-137351.m3u8"
      }
    ]
  },
  {
    "id": 5,
    "genre": "Sports",
    "payType": "P",
    "isLive": "true",
    "title": "Ethiopia VS Guinea-Bissau",
    "imageUrl": "https://images.fancode.com/aig/match/v1/137346_CASACARDS_PARTNER_16_9_1920_1080.png",
    "okassetkey": "763627649691",
    "widevine_data": {
      "kid": "627b3905d8c60f84fd164f7591a1efcf",
      "key": "b1fe5958182afaf09fba48a2c62b8fa9"
    },
    "sources": [
      {
        "name": "HLS",
        "hls": "https://live-aws-cdn.okflix.top/hls/fan1-137346.m3u8"
      }
    ]
  },
  {
    "id": 6,
    "genre": "Sports",
    "payType": "P",
    "isLive": "true",
    "title": "Libya VS Cabo Verde",
    "imageUrl": "https://images.fancode.com/aig/match/v1/137352_CASACARDS_PARTNER_16_9_1920_1080.png",
    "okassetkey": "281179856385",
    "widevine_data": {
      "kid": "7276f37d0739a83af20a2d31bcf9ac08",
      "key": "3f4a81bd029e05495acf01ec9ef0ae09"
    },
    "sources": [
      {
        "name": "HLS",
        "hls": "https://live-aws-cdn.okflix.top/hls/fan1-137352.m3u8"
      }
    ]
  },
  {
    "id": 7,
    "genre": "Sports",
    "payType": "P",
    "isLive": "true",
    "title": "United Arab Emirates VS Qatar",
    "imageUrl": "https://images.fancode.com/aig/match/v1/137175_CASACARDS_PARTNER_16_9_1920_1080.png",
    "okassetkey": "756855087013",
    "widevine_data": {
      "kid": "fff38d1ecc23f16db3d2f88002b49aa2",
      "key": "925f0a923fefad481f4da105fa02b820"
    },
    "sources": [
      {
        "name": "HLS",
        "hls": "https://live-aws-cdn.okflix.top/hls/fan1-137175.m3u8"
      }
    ]
  },
  {
    "id": 8,
    "genre": "Sports",
    "payType": "P",
    "isLive": "true",
    "title": "Afghanistan VS Bangladesh",
    "imageUrl": "https://images.fancode.com/aig/match/v1/136881_CASACARDS_PARTNER_16_9_1920_1080.png",
    "okassetkey": "325220884550",
    "widevine_data": {
      "kid": "0795bea8b59cc1c0d845a54da4c1758e",
      "key": "c2b2a3159fb1e5d718f70ccc4128f6f7"
    },
    "sources": [
      {
        "name": "HLS",
        "hls": "https://live-aws-cdn.okflix.top/hls/fan1-136881.m3u8"
      }
    ]
  }
]