[
  {
    "id": 1,
    "genre": "Cricket",
    "payType": "P",
    "isLive": "true",
    "title": "Sony Sports Ten 5",
    "imageUrl": "https://images.slivcdn.com/videoasset_images/manage_file/1000010049/1760026367682373_AsiaCup_Glory_24x7_Landscape_thumbj_9OCT_re1.jpg?h=auto&w=720&q=low",
    "okassetkey": "763702454840",
    "widevine_data": {
      "kid": "d5946c719cb922555b4d0a0e0c851c3f",
      "key": "fa707318456696629399f10b58d36902"
    },
    "sources": []
  },
  {
    "id": 2,
    "genre": "Sports",
    "payType": "P",
    "isLive": "true",
    "title": "Sharjah VS Emirates Blues",
    "imageUrl": "https://images.fancode.com/aig/match/v1/137486_CASACARDS_PARTNER_16_9_1920_1080.png",
    "okassetkey": "787054006288",
    "widevine_data": {
      "kid": "19a857d7e16f3526a9ae064a18299143",
      "key": "0878db9dc5b5aa2e0a0ee6f32916878b"
    },
    "sources": [
      {
        "name": "HLS",
        "hls": "https://live-aws-cdn.okflix.top/hls/fan1-137486.m3u8"
      }
    ]
  }
]