[
  {
    "id": 1,
    "genre": "Sports",
    "payType": "P",
    "isLive": "true",
    "title": "Toronto Blue Jays VS New York Yankees",
    "imageUrl": "https://images.fancode.com/aig/match/v1/137571_CASACARDS_PARTNER_16_9_1920_1080.png",
    "okassetkey": "936632912705",
    "widevine_data": {
      "kid": "77959fbb529523e584d8cd6c18207ad2",
      "key": "a0cc8eb470e6b27c5eca22d20ee43b00"
    },
    "sources": [
      {
        "name": "HLS",
        "hls": "https://live-aws-cdn.okflix.top/hls/fan1-137571.m3u8"
      }
    ]
  },
  {
    "id": 2,
    "genre": "Sports",
    "payType": "P",
    "isLive": "true",
    "title": "Seattle Mariners VS Detroit Tigers",
    "imageUrl": "https://images.fancode.com/aig/match/v1/137570_CASACARDS_PARTNER_16_9_1920_1080.png",
    "okassetkey": "777827972145",
    "widevine_data": {
      "kid": "3860636d012b5de40dd71dbd0e64a29e",
      "key": "fe83dbb7515e10e3d8220bf38a2e5d73"
    },
    "sources": [
      {
        "name": "HLS",
        "hls": "https://live-aws-cdn.okflix.top/hls/fan1-137570.m3u8"
      }
    ]
  },
  {
    "id": 3,
    "genre": "Sports",
    "payType": "P",
    "isLive": "true",
    "title": "New York Lions CC VS Dallas Lonestars CC",
    "imageUrl": "https://images.fancode.com/aig/match/v1/137300_CASACARDS_PARTNER_16_9_1920_1080.png",
    "okassetkey": "528824364339",
    "widevine_data": {
      "kid": "d40d063288601b5e8c1f3d7194510ce0",
      "key": "48b1d50f28d7648f9fb8bd5b58139b7c"
    },
    "sources": [
      {
        "name": "HLS",
        "hls": "https://live-aws-cdn.okflix.top/hls/fan1-137300.m3u8"
      }
    ]
  },
  {
    "id": 4,
    "genre": "Sports",
    "payType": "P",
    "isLive": "true",
    "title": "Victoria Women VS Tasmania Women",
    "imageUrl": "https://images.fancode.com/aig/match/v1/133956_CASACARDS_PARTNER_16_9_1920_1080.png",
    "okassetkey": "348127058580",
    "widevine_data": {
      "kid": "56ee8be0fddaa06a36d576f6656826b6",
      "key": "06f079d3d892e743509a273a3a3750c8"
    },
    "sources": [
      {
        "name": "HLS",
        "hls": "https://live-aws-cdn.okflix.top/hls/fan1-133956.m3u8"
      }
    ]
  }
]