[
  {
    "id": 1,
    "genre": "Sports",
    "payType": "P",
    "isLive": "true",
    "title": "Seattle Mariners VS Detroit Tigers",
    "imageUrl": "https://images.fancode.com/aig/match/v1/137570_CASACARDS_PARTNER_16_9_1920_1080.png",
    "okassetkey": "000680044721",
    "widevine_data": {
      "kid": "6413149740f8d20a5b24cf53132b13ca",
      "key": "938dcb47fc42ed2c91d6cbe5619e5a17"
    },
    "sources": [
      {
        "name": "HLS",
        "hls": "https://live-aws-cdn.okflix.top/hls/fan1-137570.m3u8"
      }
    ]
  }
]