[
  {
    "id": 1,
    "genre": "KABADDI",
    "payType": "P",
    "isLive": "true",
    "title": "Bengal Warriorz vs Dabang Delhi K.C.",
    "imageUrl": "https://img1.hotstarext.com/image/upload/w_720,q_auto:low,f_auto/sources/r1/cms/prod/7793/1759921767793-h",
    "okassetkey": "975476040450",
    "widevine_data": {
      "kid": "8957337394224583e0d47ddeeaee291e",
      "key": "5892fabbdd3825f3d4ad5f4883dd956e"
    },
    "sources": []
  },
  {
    "id": 2,
    "genre": "Archery",
    "payType": "P",
    "isLive": "true",
    "title": "LIV",
    "imageUrl": "https://images.slivcdn.com/videoasset_images/manage_file/1000009845/1759543069118452_APL25_Day8_3oct_Landscape_thumb.jpg?h=auto&w=720&q=low",
    "okassetkey": "360738429077",
    "widevine_data": {
      "kid": "81ad29de7614af3d14121ecab63a66b9",
      "key": "5cc73ac839c234ea382cca7c8787565c"
    },
    "sources": [
      {
        "name": "English",
        "language": "ENG",
        "hls": "https://live-aws-cdn.okflix.top/hls/sliv1-1090491861.m3u8"
      }
    ]
  },
  {
    "id": 3,
    "genre": "Cricket",
    "payType": "P",
    "isLive": "true",
    "title": "India W vs South Africa W",
    "imageUrl": "https://img1.hotstarext.com/image/upload/w_720,q_auto:low,f_auto/sources/r1/cms/prod/3734/1759920813734-h",
    "okassetkey": "740589038299",
    "widevine_data": {
      "kid": "fbc552fffff77fb0a07f8c6b4cbce466",
      "key": "ff1c3bf4668b690300f9c55ef81973dd"
    },
    "sources": []
  },
  {
    "id": 4,
    "genre": "Sports",
    "payType": "P",
    "isLive": "true",
    "title": "Burundi VS Kenya",
    "imageUrl": "https://images.fancode.com/aig/match/v1/137519_CASACARDS_PARTNER_16_9_1920_1080.png",
    "okassetkey": "028373835182",
    "widevine_data": {
      "kid": "23d4a72508820ecccfe302739177bdc3",
      "key": "103ee397243540d1c72e2af0dedea2bf"
    },
    "sources": [
      {
        "name": "HLS",
        "hls": "https://live-aws-cdn.okflix.top/hls/fan1-137519.m3u8"
      }
    ]
  },
  {
    "id": 5,
    "genre": "Sports",
    "payType": "P",
    "isLive": "true",
    "title": "Abu Dhabi VS Ajman",
    "imageUrl": "https://images.fancode.com/aig/match/v1/137483_CASACARDS_PARTNER_16_9_1920_1080.png",
    "okassetkey": "797362165976",
    "widevine_data": {
      "kid": "11e78e6287b24ee9ccf5288096b8270a",
      "key": "a42e148931af103868f026aaf53b4f97"
    },
    "sources": [
      {
        "name": "HLS",
        "hls": "https://live-aws-cdn.okflix.top/hls/fan1-137483.m3u8"
      }
    ]
  },
  {
    "id": 6,
    "genre": "Sports",
    "payType": "P",
    "isLive": "true",
    "title": "Papua New Guinea VS Samoa",
    "imageUrl": "https://images.fancode.com/aig/match/v1/137179_CASACARDS_PARTNER_16_9_1920_1080.png",
    "okassetkey": "575413174765",
    "widevine_data": {
      "kid": "a957d49f8987d47eff7591a6e53d8a58",
      "key": "a6814bd5c38e5fb9ffaea578e182b179"
    },
    "sources": [
      {
        "name": "HLS",
        "hls": "https://live-aws-cdn.okflix.top/hls/fan1-137179.m3u8"
      }
    ]
  },
  {
    "id": 7,
    "genre": "Sports",
    "payType": "P",
    "isLive": "true",
    "title": "Acciona Spanish Open presented by Madrid",
    "imageUrl": "https://images.fancode.com/aig/match/v1/136859_CASACARDS_PARTNER_16_9_1920_1080.png",
    "okassetkey": "696233131239",
    "widevine_data": {
      "kid": "8466ca17e6a1be5408f9d90ca2e3acd8",
      "key": "f2c3b91236874249b81519f78666bada"
    },
    "sources": [
      {
        "name": "HLS",
        "hls": "https://live-aws-cdn.okflix.top/hls/fan1-136859.m3u8"
      }
    ]
  },
  {
    "id": 8,
    "genre": "Game Show",
    "payType": "P",
    "isLive": "true",
    "title": "SET",
    "imageUrl": "https://images.slivcdn.com/videoasset_images/manage_file/1000009933/1759759561054452_KBC25_Junior_6OCT_simulcast_Landscape_Thumb.jpg?h=auto&w=720&q=low",
    "okassetkey": "091020089323",
    "widevine_data": {
      "kid": "884e0a4f2ce87edfcdbccb23666e1ee0",
      "key": "9e086df9abf65a145465f88159eefe31"
    },
    "sources": [
      {
        "name": "Hindi",
        "language": "HIN",
        "hls": "https://live-aws-cdn.okflix.top/hls/sliv1-1090486148.m3u8"
      }
    ]
  }
]