[
  {
    "id": 1,
    "genre": "Sports",
    "payType": "P",
    "isLive": "true",
    "title": "Philadelphia Phillies VS Los Angeles Dodgers",
    "imageUrl": "https://images.fancode.com/aig/match/v1/137576_CASACARDS_PARTNER_16_9_1920_1080.png",
    "okassetkey": "540606077272",
    "widevine_data": {
      "kid": "dcd14838f3c2f180f7a9b3b9215545ce",
      "key": "0accac8644bf031f7b7be0e1899b3e40"
    },
    "sources": [
      {
        "name": "HLS",
        "hls": "https://live-aws-cdn.okflix.top/hls/fan1-137576.m3u8"
      }
    ]
  },
  {
    "id": 2,
    "genre": "Sports",
    "payType": "P",
    "isLive": "true",
    "title": "Montreal Royal Tigers VS Vancouver Kings",
    "imageUrl": "https://images.fancode.com/aig/match/v1/137426_CASACARDS_PARTNER_16_9_1920_1080.png",
    "okassetkey": "495030075509",
    "widevine_data": {
      "kid": "0b5f0afbb2f4ac8ef6f67c98674a2127",
      "key": "317caf2cb5c467f31ce3a3dc68203d89"
    },
    "sources": [
      {
        "name": "HLS",
        "hls": "https://live-aws-cdn.okflix.top/hls/fan1-137426.m3u8"
      }
    ]
  },
  {
    "id": 3,
    "genre": "Sports",
    "payType": "P",
    "isLive": "true",
    "title": "Dallas Lonestars CC VS Chicago CC",
    "imageUrl": "https://images.fancode.com/aig/match/v1/137303_CASACARDS_PARTNER_16_9_1920_1080.png",
    "okassetkey": "370735481953",
    "widevine_data": {
      "kid": "f2bea1d92d717ff7cdd40c45867621fb",
      "key": "d10b7aedf2b50cb7637fcccb8bc55a09"
    },
    "sources": [
      {
        "name": "HLS",
        "hls": "https://live-aws-cdn.okflix.top/hls/fan1-137303.m3u8"
      }
    ]
  },
  {
    "id": 4,
    "genre": "Sports",
    "payType": "P",
    "isLive": "true",
    "title": "Victoria Women VS Tasmania Women",
    "imageUrl": "https://images.fancode.com/aig/match/v1/133957_CASACARDS_PARTNER_16_9_1920_1080.png",
    "okassetkey": "237460550700",
    "widevine_data": {
      "kid": "2c6774295eb33f6c4dc634380ac66e43",
      "key": "e49b1ea711ea5aae47081168b3c9a143"
    },
    "sources": [
      {
        "name": "HLS",
        "hls": "https://live-aws-cdn.okflix.top/hls/fan1-133957.m3u8"
      }
    ]
  }
]