[
  {
    "id": 1,
    "genre": "Cricket",
    "payType": "P",
    "isLive": "true",
    "title": "2nd Test: India vs West Indies, Day 2",
    "imageUrl": "https://img1.hotstarext.com/image/upload/w_720,q_auto:low,f_auto/sources/r1/cms/prod/7730/1760094947730-h",
    "okassetkey": "695857228094",
    "widevine_data": {
      "kid": "47dadd0456e3c11c7dd7f7d6a16a01e5",
      "key": "0ffdb58bacaeec83d03c23a204113214"
    },
    "sources": []
  },
  {
    "id": 2,
    "genre": "Cricket",
    "payType": "P",
    "isLive": "true",
    "title": "Sony Sports Ten 5",
    "imageUrl": "https://images.slivcdn.com/videoasset_images/manage_file/1000010049/1760026367682373_AsiaCup_Glory_24x7_Landscape_thumbj_9OCT_re1.jpg?h=auto&w=720&q=low",
    "okassetkey": "548176762176",
    "widevine_data": {
      "kid": "051537d71fa54e3311608c7fa7b9fe71",
      "key": "a23da67690fd8e149d384c85ae1c757e"
    },
    "sources": []
  },
  {
    "id": 3,
    "genre": "Sports",
    "payType": "P",
    "isLive": "true",
    "title": "Tamil Nadu Chief Minister\u2019s Trophy Games 2025",
    "imageUrl": "https://images.fancode.com/aig/match/v1/137621_CASACARDS_PARTNER_16_9_1920_1080.png",
    "okassetkey": "064753374123",
    "widevine_data": {
      "kid": "8115dce103c3f72da04d2b94df0993b8",
      "key": "23f9ce52189960e06629bd0b705bfa76"
    },
    "sources": [
      {
        "name": "HLS",
        "hls": "https://live-aws-cdn.okflix.top/hls/fan1-137621.m3u8"
      }
    ]
  },
  {
    "id": 4,
    "genre": "Sports",
    "payType": "P",
    "isLive": "true",
    "title": "Detroit Tigers VS Seattle Mariners",
    "imageUrl": "https://images.fancode.com/aig/match/v1/137578_CASACARDS_PARTNER_16_9_1920_1080.png",
    "okassetkey": "202282658728",
    "widevine_data": {
      "kid": "bc6e0b68209964b8d15cde25da267c43",
      "key": "f925f41e8f2ab78d72ed6d06652de046"
    },
    "sources": [
      {
        "name": "HLS",
        "hls": "https://live-aws-cdn.okflix.top/hls/fan1-137578.m3u8"
      }
    ]
  },
  {
    "id": 5,
    "genre": "Sports",
    "payType": "P",
    "isLive": "true",
    "title": "Baycurrent Classic",
    "imageUrl": "https://images.fancode.com/aig/match/v1/137313_CASACARDS_PARTNER_16_9_1920_1080.png",
    "okassetkey": "292531616260",
    "widevine_data": {
      "kid": "d40db1170ddaefc0be04a041f1e926c3",
      "key": "ed66f7f37f0f7f33faaab706b186ee74"
    },
    "sources": [
      {
        "name": "HLS",
        "hls": "https://live-aws-cdn.okflix.top/hls/fan1-137313.m3u8"
      }
    ]
  },
  {
    "id": 6,
    "genre": "Sports",
    "payType": "P",
    "isLive": "true",
    "title": "New South Wales Breakers VS Western Australia Women",
    "imageUrl": "https://images.fancode.com/aig/match/v1/133959_CASACARDS_PARTNER_16_9_1920_1080.png",
    "okassetkey": "319071204824",
    "widevine_data": {
      "kid": "38cc764ab3c7ce9ae571f7dbd4419bc5",
      "key": "64b77c2d649638964939f05834a6b92a"
    },
    "sources": []
  }
]